{
  "match_analysis": {
    "generated_at": "2025-07-06T19:15:00Z",
    "source": "GAA Video Analysis Pipeline - Manual Verification",
    "model": "Gemini 2.5 Flash + Manual Verification",
    "video_duration": "84:00",
    "clips_analyzed": 337,
    "analysis_type": "halftime_detection_verified"
  },
  "match_timeline": {
    "pre_match": {
      "start": "00:00",
      "end": "02:15",
      "duration_minutes": 2.25,
      "description": "Pre-match warm-up and preparation"
    },
    "first_half": {
      "start": "02:15",
      "end": "33:00",
      "duration_minutes": 30.75,
      "description": "First half competitive play - starts with active match play"
    },
    "halftime": {
      "start": "33:00",
      "end": "48:45",
      "duration_minutes": 15.75,
      "description": "Halftime break with warm-up activities"
    },
    "second_half": {
      "start": "48:45",
      "end": "83:00",
      "duration_minutes": 34.25,
      "description": "Second half competitive play - starts with referee throw-in ceremony"
    },
    "post_match": {
      "start": "83:00",
      "end": "84:00",
      "duration_minutes": 1.0,
      "description": "Post-match conclusion - players leaving field"
    }
  },
  "key_events": [
    {
      "event": "first_half_start",
      "timestamp": "02:15",
      "description": "First half begins - First clip with explicit 'active match play'",
      "type": "match_transition",
      "reasoning": "The description for clip_02m15s.txt is the very first one that explicitly states 'active match play' is happening. All previous clips are described as 'warm-up' or 'preparation.'"
    },
    {
      "event": "first_half_end",
      "timestamp": "33:00",
      "description": "First half ends - Last moment of active play before halftime",
      "type": "match_transition",
      "reasoning": "This remains the last moment of described active play before the descriptions clearly shift to a long 'practice or warm-up session' (the half-time break) starting at 33:45."
    },
    {
      "event": "second_half_start",
      "timestamp": "48:45",
      "description": "Second half begins - Referee performing GAA throw-in ceremony",
      "type": "match_transition",
      "reasoning": "This is the first clip after the long half-time break that explicitly describes the 'referee performing the GAA throw-in ceremony,' which is the official restart of the half."
    },
    {
      "event": "match_end",
      "timestamp": "83:00",
      "description": "Match ends - Last on-field action before players disperse",
      "type": "match_transition",
      "reasoning": "This is the last described on-field action before the clips at 83:15 and 83:30 show players dispersing and leaving the field, with the description noting it is likely the 'end of a half or match.'"
    }
  ],
  "match_statistics": {
    "total_match_duration_minutes": 65.0,
    "actual_playing_time_minutes": 65.0,
    "break_time_minutes": 19.0,
    "first_half_duration_minutes": 30.75,
    "halftime_duration_minutes": 15.75,
    "second_half_duration_minutes": 34.25
  },
  "verification": {
    "method": "Manual verification of AI analysis",
    "verified_by": "User review of clip descriptions",
    "confidence": "High - based on explicit clip descriptions",
    "last_updated": "2025-07-06T19:15:00Z"
  }
} 